zabbix_feishu_alert/__init__.py
zabbix_feishu_alert/message.py
zabbix_feishu_alert/message_base.py
zabbix_feishu_alert-1.0.7.dist-info/METADATA
zabbix_feishu_alert-1.0.7.dist-info/WHEEL
zabbix_feishu_alert-1.0.7.dist-info/top_level.txt
zabbix_feishu_alert-1.0.7.dist-info/RECORD
