Metadata-Version: 2.1
Name: zabbix-feishu-alert
Version: 1.0.7
Summary: zabbix send alert message and graph to feishu robot
Home-page: https://github.com/yinhuanyi/zabbix-feishu-alert
Author: Robby
Author-email: yinhuanyicn@gmail.com
License: MIT
Platform: UNKNOWN
Requires-Dist: requests
